ovisu/README.md
ovisu/internal/__init__.py
ovisu/internal/api/__init__.py
ovisu/internal/api/dependencies/__init__.py
ovisu/internal/api/dependencies/auth.py
ovisu/internal/api/dependencies/s3.py
ovisu/internal/api/v1/__init__.py
ovisu/internal/api/v1/endpoints/__init__.py
ovisu/internal/api/v1/endpoints/auth.py
ovisu/internal/api/v1/endpoints/bucket.py
ovisu/internal/api/v1/endpoints/keychain.py
ovisu/internal/api/v1/schema/request/bucket.py
ovisu/internal/api/v1/schema/request/keychain.py
ovisu/internal/api/v1/schema/request/user.py
ovisu/internal/api/v1/schema/response/__init__.py
ovisu/internal/api/v1/schema/response/bucket.py
ovisu/internal/api/v1/schema/response/keychain.py
ovisu/internal/api/v1/schema/response/user.py
ovisu/internal/client/s3_reader.py
ovisu/internal/common/db.py
ovisu/internal/common/exceptions.py
ovisu/internal/common/io.py
ovisu/internal/config.py
ovisu/internal/crud/__init__.py
ovisu/internal/crud/base.py
ovisu/internal/crud/bucket.py
ovisu/internal/crud/keychain.py
ovisu/internal/crud/user.py
ovisu/internal/middleware/__init__.py
ovisu/internal/middleware/content_type.py
ovisu/internal/middleware/tracing.py
ovisu/internal/models/__init__.py
ovisu/internal/models/bucket.py
ovisu/internal/models/keychain.py
ovisu/internal/models/user.py
ovisu/internal/schema/__init__.py
ovisu/internal/schema/keychain.py
ovisu/internal/schema/state.py
ovisu/internal/schema/user.py
ovisu/internal/service/bucket.py
ovisu/internal/statics/__init__.py
ovisu/internal/statics/aliyun.png
ovisu/internal/statics/assets/CloseOutlined-Bqr7nz7m.js
ovisu/internal/statics/assets/UserOutlined-BTv1y14-.js
ovisu/internal/statics/assets/index-B-uz61di.css
ovisu/internal/statics/assets/index-BDN0QuQ8.js
ovisu/internal/statics/assets/index-BJScDE9_.js
ovisu/internal/statics/assets/index-BgSJljk1.js
ovisu/internal/statics/assets/index-CHtTHo2p.css
ovisu/internal/statics/assets/index-CMkRNDRS.js
ovisu/internal/statics/assets/index-CZmce9BG.js
ovisu-1.0.0a8.dist-info/LICENSE
ovisu-1.0.0a8.dist-info/METADATA
ovisu-1.0.0a8.dist-info/WHEEL
ovisu-1.0.0a8.dist-info/entry_points.txt
ovisu-1.0.0a8.dist-info/RECORD
