Metadata-Version: 2.3
Name: ovisu
Version: 1.0.0a8
Summary: Visualize s3 data
License: Apache 2.0
Author: shenguanlin
Author-email: shenguanlin@pjlab.org.cn
Requires-Python: ==3.11.*
Classifier: License :: Other/Proprietary License
Classifier: Programming Language :: Python :: 3
Classifier: Programming Language :: Python :: 3.11
Requires-Dist: alembic (>=1.15.2,<2.0.0)
Requires-Dist: appdirs (>=1.4.4,<2.0.0)
Requires-Dist: beautifulsoup4 (>=4.13.4,<5.0.0)
Requires-Dist: boto3 (>=1.38.14,<2.0.0)
Requires-Dist: cchardet (==2.2.0a2)
Requires-Dist: cryptography (>=44.0.3,<45.0.0)
Requires-Dist: ebooklib (>=0.19,<0.20)
Requires-Dist: fastapi (>=0.115.12,<0.116.0)
Requires-Dist: fastwarc (>=0.15.2,<0.16.0)
Requires-Dist: httpx (>=0.28.1,<0.29.0)
Requires-Dist: loguru (>=0.6.0,<0.7.0)
Requires-Dist: mobi (>=0.3.3,<0.4.0)
Requires-Dist: orjson (>=3.10.18,<4.0.0)
Requires-Dist: passlib[bcrypt] (>=1.7.4,<2.0.0)
Requires-Dist: pydantic (>=2.11.4,<3.0.0)
Requires-Dist: pydantic-settings (>=2.9.1,<3.0.0)
Requires-Dist: python-jose (>=3.4.0,<4.0.0)
Requires-Dist: python-magic (>=0.4.27,<0.5.0)
Requires-Dist: python-multipart (>=0.0.20,<0.0.21)
Requires-Dist: sqlalchemy (>=2.0.40,<3.0.0)
Requires-Dist: typer[all] (>=0.15.3,<0.16.0)
Requires-Dist: uvicorn (>=0.34.2,<0.35.0)
Requires-Dist: warcio (>=1.7.5,<2.0.0)
Project-URL: Repository, https://github.com/OpenDataLab/VisU
